{
  "key": [
    "numtype",
    "bronze",
    "silver",
    "gold",
    "platinum",
    "maximum",
    "monotonic",
    "required",
    "icon",
    "category"
  ],
  "data":
  {
    "Total XP":
      ["Integer",0,0,0,0,-1,true,1,"total_xp","General"],
    "Trainer Level":
      ["Integer",0,0,0,0,80,true,1,"trainer_level","General"],
    "Pokédex: Total":
      ["Integer",0,0,0,0,934,true,1,"pokedex_caught","Pokédex"],
    "Pokédex: Shiny":
      ["Integer",0,0,0,0,857,true,1,"pokedex_shiny","Pokédex"],
    "Pokédex: Lucky":
      ["Integer",0,0,0,0,917,true,1,"pokedex_lucky","Pokédex"],
    "Pokédex: XXL":
      ["Integer",0,0,0,0,934,true,1,"pokedex_xxl","Pokédex"],
    "Pokédex: XXS":
      ["Integer",0,0,0,0,934,true,1,"pokedex_xxs","Pokédex"],
    "Pokédex: G-Max":
      ["Integer",0,0,0,0,15,true,1,"pokedex_gmax","Pokédex"],
    "Pokédex: Mega":
      ["Integer",0,0,0,0,48,true,1,"pokedex_mega","Pokédex"],
    "Pokédex: Shadow":
      ["Integer",0,0,0,0,420,true,1,"pokedex_shadow","Pokédex"],
    "Pokédex: Purified":
      ["Integer",0,0,0,0,420,true,1,"pokedex_purified","Pokédex"],
    "Pokédex: ★ 100%":
      ["Integer",0,0,0,0,934,true,1,"pokedex_4star","Pokédex"],
    "Unique Species Seen":
      ["Integer",0,0,0,0,934,true,-1,"pokedex_seen","Pokédex"],
    "Unknown Generation":
      ["Integer",0,0,0,0,2,true,-1,"pokedex_entries_unknown","Pokédex"],
    "Pokédex: 3 Stars":
      ["Integer",0,0,0,0,934,true,-1,"pokedex_3star","Pokédex"],
    "Pokédex: Shiny 3 Stars":
      ["Integer",0,0,0,0,857,true,-1,"pokedex_3star_shiny","Pokédex"],
    "Pokédex: Event/Costume":
      ["Integer",0,0,0,0,279,true,-1,"pokedex_event","Pokédex"],
    "Stardust":
      ["Integer",0,0,0,0,-1,false,0,"pokemon_info_stardust","General"],
    "Go Battle League - Overall Wins":
      ["Integer",0,0,0,0,-1,true,1,"go_battle_league_overall_wins","Battle"],
    "Go Battle League - Overall Played":
      ["Integer",0,0,0,0,-1,true,1,"go_battle_league_overall_played","Battle"],
    "Go Battle League - Overall Streak":
      ["Integer",0,0,0,0,-1,true,1,"go_battle_league_overall_streak","Battle"],
    "Completed Special/Timed Research":
      ["Integer",0,0,0,0,-1,true,0,"completed_special_research","Research"],
    "Unique Route Badges":
      ["Integer",0,0,0,0,-1,true,0,"routes_completed","Exploration"],
    "Gym Badges":
      ["Integer",0,0,0,0,2000,true,0,"gymbadges_total","Gym"],
    "Gold Gym Badges":
      ["Integer",0,0,0,0,-1,true,0,"gymbadges_gold","Gym"],
    "Elite Collector":
      ["Integer",0,0,0,0,-1,true,1,"elite_collector_challenge","Medal","comment: being lazy on maximum here"],
    "Jogger":
      ["Float",10,100,1000,10000,-1,true,0,"travel_km","Medal"],
    "Kanto":
      ["Integer",5,50,100,151,151,true,1,"pokedex_entries","Regional"],
    "Collector":
      ["Integer",30,500,2000,50000,-1,true,1,"capture_total","Medal"],
    "Scientist":
      ["Integer",3,20,200,2000,-1,true,1,"evolved_total","Medal"],
    "Breeder":
      ["Integer",10,100,500,2500,-1,true,1,"hatched_total","Medal"],
    "Backpacker":
      ["Integer",100,1000,2000,50000,-1,true,1,"pokestops_visited","Medal"],
    "Sightseer":
      ["Integer",10,100,1000,2000,-1,true,1,"pokestops_visited_unique","Medal"],
    "Fisher":
      ["Integer",3,50,300,1000,-1,true,1,"big_magikarp","Medal"],
    "Battle Girl":
      ["Integer",10,100,1000,4000,-1,true,1,"battle_attack_won","Medal"],
    "Ace Trainer":
      ["Integer",10,100,1000,2000,-1,true,1,"battle_training_won","Medal"],
    "Youngster":
      ["Integer",3,50,300,1000,-1,true,1,"small_rattata","Medal"],
    "Pikachu Fan":
      ["Integer",3,50,300,1000,-1,true,1,"pikachu","Medal"],
    "Unown":
      ["Integer",3,10,26,28,28,true,1,"unown","Medal"],
    "Johto":
      ["Integer",5,30,70,100,100,true,1,"pokedex_entries_gen2","Regional"],
    "Champion":
      ["Integer",10,100,1000,2000,-1,true,1,"raid_battle_won","Medal"],
    "Battle Legend":
      ["Integer",10,100,1000,2000,-1,true,1,"legendary_battle_won","Medal"],
    "Berry Master":
      ["Integer",10,100,1000,15000,-1,true,1,"berries_fed","Medal"],
    "Gym Leader":
      ["Integer",10,100,1000,15000,-1,true,1,"hours_defended","Medal"],
    "Hoenn":
      ["Integer",5,40,90,135,135,true,1,"pokedex_entries_gen3","Regional"],
    "Pokémon Ranger":
      ["Integer",10,100,1000,2500,-1,true,1,"challenge_quests","Medal"],
    "Idol":
      ["Integer",1,2,3,20,-1,true,1,"max_level_friends","Social"],
    "Gentleman":
      ["Integer",10,100,1000,2500,-1,true,1,"trading","Social"],
    "Pilot":
      ["Integer",1000,100000,1000000,10000000,-1,true,1,"trading_distance","Social"],
    "Sinnoh":
      ["Integer",5,30,80,107,104,true,1,"pokedex_entries_gen4","Regional"],
    "Great League Veteran":
      ["Integer",5,50,200,1000,-1,true,1,"great_league","Battle"],
    "Ultra League Veteran":
      ["Integer",5,50,200,1000,-1,true,1,"ultra_league","Battle"],
    "Master League Veteran":
      ["Integer",5,50,200,1000,-1,true,1,"master_league","Battle"],
    "Cameraman":
      ["Integer",10,50,200,400,-1,true,1,"photobomb","Medal"],
    "Unova":
      ["Integer",5,50,100,156,156,true,1,"pokedex_entries_gen5","Regional"],
    "Purifier":
      ["Integer",5,50,500,1000,-1,true,1,"purifier","Medal"],
    "Hero":
      ["Integer",10,100,1000,2000,-1,true,1,"hero","Medal"],
    "Ultra Hero":
      ["Integer",1,5,20,50,-1,true,1,"ultra_hero","Medal"],
    "Best Buddy":
      ["Integer",1,10,100,200,-1,true,1,"best_buddy","Social"],
    "Kalos":
      ["Integer",5,25,50,72,72,true,1,"pokedex_entries_gen6","Regional"],
    "Alola":
      ["Integer",5,25,50,86,78,true,1,"pokedex_entries_gen7","Regional"],
    "Galar":
      ["Integer",5,25,50,89,66,true,1,"pokedex_entries_gen8","Regional"],
    "Triathlete":
      ["Integer",1,10,50,100,-1,true,1,"pokestreak","Medal"],
    "Rising Star":
      ["Integer",2,10,50,150,-1,true,1,"raid_battle_unique","Medal"],
    "Rising Star Duo":
      ["Integer",10,100,1000,2000,-1,true,1,"raid_battle_friends","Medal"],
    "Picnicker":
      ["Integer",5,25,500,2500,-1,true,1,"lure_module_catches","Medal"],
    "Wayfarer":
      ["Integer",50,500,1000,1500,-1,true,0,"wayfarer_agreements","Exploration"],
    "Successor":
      ["Integer",1,50,500,1000,-1,true,1,"mega_evolves","Medal"],
    "Mega/Primal Evolution Guru":
      ["Integer",1,24,36,46,48,true,1,"pokedex_entries_mega_dex","Medal"],
    "Friend Finder":
      ["Integer",1,10,20,50,-1,true,0,"referral","Social"],
    "Raid Expert":
      ["Integer",1,50,200,500,-1,true,1,"raid_expert","Medal"],
    "Expert Navigator":
      ["Integer",10,50,200,600,-1,true,0,"routes_trips","Exploration"],
    "Paldea":
      ["Integer",5,30,80,103,64,true,1,"pokedex_entries_gen10","Regional"],
    "Hisui":
      ["Integer",1,3,5,7,6,true,1,"pokedex_entries_gen9","Regional"],
    "Tiny Pokémon Collector":
      ["Integer",5,25,100,500,-1,true,1,"tinycollector","Medal"],
    "Jumbo Pokémon Collector":
      ["Integer",5,25,100,500,-1,true,1,"jumbocollector","Medal"],
    "Life of the Party":
      ["Integer",10,50,100,200,-1,true,1,"lifeofparty","Social"],
    "Community Member":
      ["Integer",1,20,50,100,-1,true,1,"community_member","Social"],
    "Showcase Star":
      ["Integer",1,10,50,100,-1,true,0,"showcase","Social"],
    "Vivillon Collector":
      ["Integer",3,10,15,18,18,true,1,"vivilloncollector","Medal"],
    "Schoolkid":
      ["Integer",10,50,200,2500,-1,true,0,"type_normal","Type"],
    "Black Belt":
      ["Integer",10,50,200,2500,-1,true,0,"type_fighting","Type"],
    "Bird Keeper":
      ["Integer",10,50,200,2500,-1,true,0,"type_flying","Type"],
    "Punk Girl":
      ["Integer",10,50,200,2500,-1,true,0,"type_poison","Type"],
    "Ruin Maniac":
      ["Integer",10,50,200,2500,-1,true,0,"type_ground","Type"],
    "Hiker":
      ["Integer",10,50,200,2500,-1,true,0,"type_rock","Type"],
    "Bug Catcher":
      ["Integer",10,50,200,2500,-1,true,0,"type_bug","Type"],
    "Hex Maniac":
      ["Integer",10,50,200,2500,-1,true,0,"type_ghost","Type"],
    "Rail Staff":
      ["Integer",10,50,200,2500,-1,true,0,"type_steel","Type"],
    "Kindler":
      ["Integer",10,50,200,2500,-1,true,0,"type_fire","Type"],
    "Swimmer":
      ["Integer",10,50,200,2500,-1,true,0,"type_water","Type"],
    "Gardener":
      ["Integer",10,50,200,2500,-1,true,0,"type_grass","Type"],
    "Rocker":
      ["Integer",10,50,200,2500,-1,true,0,"type_electric","Type"],
    "Psychic":
      ["Integer",10,50,200,2500,-1,true,0,"type_psychic","Type"],
    "Skier":
      ["Integer",10,50,200,2500,-1,true,0,"type_ice","Type"],
    "Dragon Tamer":
      ["Integer",10,50,200,2500,-1,true,0,"type_dragon","Type"],
    "Delinquent":
      ["Integer",10,50,200,2500,-1,true,0,"type_dark","Type"],
    "Fairy Tale Girl":
      ["Integer",10,50,200,2500,-1,true,0,"type_fairy","Type"]
  }
}
